{
  "title": "Simple and Transparent Pricing",
  "subTitle": "Boost your academic performance with TutorMe's tailored tutoring packages.",
  "badge": "Most Popular",
  "thirdOption": "School Programs?",
  "btnText": "Get a Custom Quote",

  "elementarySchool": {
    "name": "Elementary School",
    "description": "Prices Starting from",
    "price": "$50",
    "cents": "",
    "billingFrequency": "/hr",
    "features": [
      "Personalized learning plans",
      "Basic subjects coverage",
      "Interactive learning games",
      "Parent-teacher communication"
    ],
    "purchaseBtnTitle": "Choose Elementary Package",
    "purchaseLink": "#"
  },

  "middleSchool": {
    "name": "Middle School",
    "description": "Prices Starting from",
    "price": "$50",
    "cents": "",
    "billingFrequency": "/hr",
    "features": [
      "Advanced subject specialization",
      "Study skills development",
      "Test preparation support",
      "Progress reports and feedback"
    ],
    "purchaseBtnTitle": "Choose Middle School Package",
    "purchaseLink": "#"
  },

  "highSchool": {
    "name": "High School",
    "description": "Prices Starting from",
    "price": "$55",
    "cents": "",
    "billingFrequency": "/hr",
    "features": [
      "AP and IB course support",
      "SAT/ACT prep materials",
      "College admissions guidance",
      "Career exploration resources"
    ],
    "purchaseBtnTitle": "Choose High School Package",
    "purchaseLink": "#"
  },

  "college": {
    "name": "College",
    "description": "Prices Starting from",
    "price": "$65",
    "cents": "",
    "billingFrequency": "/hr",
    "features": [
      "Advanced topic expertise",
      "Research paper assistance",
      "Exam preparation strategies",
      "Graduate school application support"
    ],
    "purchaseBtnTitle": "Choose College Package",
    "purchaseLink": "#"
  }
}